MANIFEST.in
README.txt
setup.py
bin/pg_monitor
pg_monitor/__init__.py
pg_monitor/backends.py
pg_monitor/bloats.py
pg_monitor/checkStatus.py
pg_monitor/connection.py
pg_monitor/defaults.py
pg_monitor/duplicateIndexes.py
pg_monitor/factors.py
pg_monitor/helpText.py
pg_monitor/hexa.py
pg_monitor/locks.py
pg_monitor/monitor.py
pg_monitor/perfdataText.py
pg_monitor/relationSizes.py
pg_monitor/replicaLag.py
pg_monitor/sql.py
pg_monitor/vacuum.py
pg_monitor/wals.py
pg_monitor.egg-info/PKG-INFO
pg_monitor.egg-info/SOURCES.txt
pg_monitor.egg-info/dependency_links.txt
pg_monitor.egg-info/not-zip-safe
pg_monitor.egg-info/requires.txt
pg_monitor.egg-info/top_level.txt