Metadata-Version: 1.1
Name: pg-monitor
Version: 1.5.8
Summary: PostgreSQL monitoring checks
Home-page: https://github.com/rugging24/pg_monitor
Author: Olakunle Olaniyi
Author-email: rugging24@gmail.com
License: PostgreSQL License
Platform: UNKNOWN
Classifier: Development Status :: 5 - Production/Stable
Classifier: License :: OSI Approved :: MIT License
Classifier: Programming Language :: Python :: 2.7
Classifier: Topic :: System :: Networking :: Monitoring
